simpla/__init__.py
simpla/_config.py
simpla/_platoon.py
simpla/_platoonmanager.py
simpla/_platoonmode.py
simpla/_pvehicle.py
simpla/_reporting.py
simpla/_utils.py
sumolib/__init__.py
sumolib/color.py
sumolib/fpdiff.py
sumolib/geomhelper.py
sumolib/miscutils.py
sumolib/options.py
sumolib/route.py
sumolib/statistics.py
sumolib/translation.py
sumolib/vehicletype.py
sumolib/version.py
sumolib/xml.py
sumolib/datastructures/OrderedMultiSet.py
sumolib/datastructures/__init__.py
sumolib/files/__init__.py
sumolib/files/additional.py
sumolib/files/selection.py
sumolib/net/__init__.py
sumolib/net/connection.py
sumolib/net/edge.py
sumolib/net/lane.py
sumolib/net/netshiftadaptor.py
sumolib/net/node.py
sumolib/net/roundabout.py
sumolib/net/generator/__init__.py
sumolib/net/generator/corridor.py
sumolib/net/generator/cross.py
sumolib/net/generator/demand.py
sumolib/net/generator/grid.py
sumolib/net/generator/network.py
sumolib/net/generator/straight.py
sumolib/output/__init__.py
sumolib/output/dump.py
sumolib/output/inductionloop.py
sumolib/output/convert/__init__.py
sumolib/output/convert/fcdfilter.py
sumolib/output/convert/gpsdat.py
sumolib/output/convert/gpx.py
sumolib/output/convert/ipg.py
sumolib/output/convert/keplerjson.py
sumolib/output/convert/kml.py
sumolib/output/convert/ns2.py
sumolib/output/convert/omnet.py
sumolib/output/convert/phem.py
sumolib/output/convert/poi.py
sumolib/output/convert/shawn.py
sumolib/output/convert/trj.py
sumolib/scenario/__init__.py
sumolib/scenario/checkFlows.py
sumolib/scenario/pop2.py
sumolib/scenario/runsdb.py
sumolib/scenario/scenarios/__init__.py
sumolib/scenario/scenarios/basic_corridor.py
sumolib/scenario/scenarios/basic_cross.py
sumolib/scenario/scenarios/basic_crossl.py
sumolib/scenario/scenarios/basic_net.py
sumolib/scenario/scenarios/basic_rilsacorridor3.py
sumolib/scenario/scenarios/basic_rilsanet.py
sumolib/scenario/scenarios/basic_rilsanet2x2.py
sumolib/scenario/scenarios/real_world.py
sumolib/scenario/scenarios/rilsa1.py
traci-1.23.0.dist-info/METADATA
traci-1.23.0.dist-info/WHEEL
traci-1.23.0.dist-info/top_level.txt
traci-1.23.0.dist-info/RECORD
