Metadata-Version: 2.4
Name: traci
Version: 1.23.0
Summary: The pure python version of the TraCI API to communicate with the traffic simulation Eclipse SUMO
Home-page: https://sumo.dlr.de/docs/TraCI/Interfacing_TraCI_from_Python.html
Download-URL: https://sumo.dlr.de/download
Author: DLR and contributors
Author-email: sumo@dlr.de
License: EPL-2.0
Keywords: traffic simulation traci sumo
Classifier: Development Status :: 5 - Production/Stable
Classifier: Intended Audience :: Developers
Classifier: Intended Audience :: Science/Research
Classifier: Programming Language :: Python :: 2
Classifier: Programming Language :: Python :: 3
Requires-Dist: sumolib>=1.23.0
Dynamic: author
Dynamic: author-email
Dynamic: classifier
Dynamic: description
Dynamic: description-content-type
Dynamic: download-url
Dynamic: home-page
Dynamic: keywords
Dynamic: license
Dynamic: requires-dist
Dynamic: summary
